findicator/__init__.py
findicator/atr.py
findicator/bollinger.py
findicator/elder_ray.py
findicator/ema_channel.py
findicator/force_index.py
findicator/impulse_system.py
findicator/macd.py
findicator/rsi.py
findicator/stochastic.py
findicator-0.1.11.dist-info/LICENSE
findicator-0.1.11.dist-info/METADATA
findicator-0.1.11.dist-info/WHEEL
findicator-0.1.11.dist-info/RECORD
