Metadata-Version: 2.3
Name: findicator
Version: 0.1.11
Summary: A modern Python library for financial indicators
License: MIT
Author: Refen
Author-email: abbasi.seyed.alireza@gmail.com
Requires-Python: >=3.9
Classifier: License :: OSI Approved :: MIT License
Classifier: Programming Language :: Python :: 3
Classifier: Programming Language :: Python :: 3.9
Classifier: Programming Language :: Python :: 3.10
Classifier: Programming Language :: Python :: 3.11
Classifier: Programming Language :: Python :: 3.12
Classifier: Programming Language :: Python :: 3.13
Requires-Dist: pandas (>=2.0,<3.0)
Project-URL: Repository, https://github.com/RefenRefen/findicator
